censeye/__init__.py
censeye/__main__.py
censeye/__version__.py
censeye/aggregator.py
censeye/censeye.py
censeye/cli.py
censeye/config.py
censeye/const.py
censeye/gadget.py
censeye/vt.py
censeye/gadgets/__init__.py
censeye/gadgets/nobbler.py
censeye/gadgets/opendir.py
censeye/gadgets/threatfox.py
censeye/gadgets/vt.py
censeye-1.0.1.dist-info/LICENSE
censeye-1.0.1.dist-info/METADATA
censeye-1.0.1.dist-info/WHEEL
censeye-1.0.1.dist-info/entry_points.txt
censeye-1.0.1.dist-info/top_level.txt
censeye-1.0.1.dist-info/RECORD
