Metadata-Version: 2.1
Name: censeye
Version: 1.0.1
Summary: This tool is designed to help researchers identify hosts with characteristics similar to a given target.
Home-page: https://github.com/Censys-Research/censeye
Author: Censys, Inc.
Author-email: support@censys.io
License: BSD
Classifier: Topic :: Security
Classifier: Topic :: Utilities
Classifier: Environment :: Console
Classifier: Intended Audience :: Information Technology
Classifier: Intended Audience :: Science/Research
Classifier: License :: OSI Approved :: BSD License
Classifier: Programming Language :: Python
Classifier: Programming Language :: Python :: 3
Classifier: Programming Language :: Python :: 3.9
Classifier: Programming Language :: Python :: 3.10
Classifier: Programming Language :: Python :: 3.11
Requires-Python: >=3.9.0
License-File: LICENSE
Requires-Dist: appdirs==1.4.4
Requires-Dist: backoff==2.2.1
Requires-Dist: beautifulsoup4==4.12.3
Requires-Dist: censys==2.2.16
Requires-Dist: click==8.1.7
Requires-Dist: python_dateutil==2.9.0.post0
Requires-Dist: PyYAML==6.0.2
Requires-Dist: Requests==2.32.3
Requires-Dist: rich==13.9.4
Requires-Dist: setuptools>70.0.0
Provides-Extra: dev
Requires-Dist: twine; extra == "dev"
Requires-Dist: black; extra == "dev"
Requires-Dist: isort; extra == "dev"
Requires-Dist: pyupgrade; extra == "dev"
Requires-Dist: flake8; extra == "dev"
Requires-Dist: flake8-bugbear; extra == "dev"
